{"Windows 10 x64": {
    "path": "f:\\Images\\Windows 10 x64\\Windows 10 x64.vmx",
    "lang": "English",
    "winver": "10",
	"win_name": "vm-win10",
    "cad_family": {
		 "Catia": [
			{ "snap": "Catia R19",       			"production": 0, "show": 0, "prefix": "EFD.V5-" },
			{ "snap": "Catia R20",       			"production": 0, "show": 0, "prefix": "EFD.V5-" },
			{ "snap": "Catia R21",       			"production": 0, "show": 1, "prefix": "EFD.V5-" },
			{ "snap": "Catia R22",       			"production": 0, "show": 0, "prefix": "EFD.V5-" },
			{ "snap": "Catia R23",       			"production": 0, "show": 0, "prefix": "EFD.V5-" },
			{ "snap": "Catia R24",       			"production": 0, "show": 1, "prefix": "EFD.V5-" },
			{ "snap": "Catia R25",       			"production": 0, "show": 1, "prefix": "EFD.V5-" },
			{ "snap": "Catia R26",       			"production": 0, "show": 1, "prefix": "EFD.V5-" },
			{ "snap": "Catia R27",       			"production": 0, "show": 1, "prefix": "EFD.V5-" },
			{ "snap": "Catia R28",       			"production": 0, "show": 1, "prefix": "EFD.V5-" },
			{ "snap": "Catia R29",       			"production": 0, "show": 1, "prefix": "EFD.V5-" },
			{ "snap": "Catia R30",       			"production": 0, "show": 1, "prefix": "EFD.V5-" }
			],
		 "Creo": [
	        { "snap": "Creo 2.0",        			"production": 0, "show": 0, "prefix": "EFD.PRO-" },
			{ "snap": "Creo 3.0",        			"production": 0, "show": 1, "prefix": "EFD.PRO-" },
			{ "snap": "Creo 4.0",        			"production": 0, "show": 1, "prefix": "EFD.PRO-" },
			{ "snap": "Creo 5.0",        			"production": 0, "show": 1, "prefix": "EFD.PRO-" },
			{ "snap": "Creo 6.0",        			"production": 0, "show": 1, "prefix": "EFD.PRO-" },
			{ "snap": "Creo 7.0",        			"production": 0, "show": 1, "prefix": "EFD.PRO-" }
			],
		 "NX": [
			{ "snap": "NX 9.0",          			"production": 0, "show": 0, "prefix": "EFD.NX-" },
			{ "snap": "NX 10.0",         			"production": 0, "show": 1, "prefix": "EFD.NX-" },
			{ "snap": "NX 11.0",         			"production": 0, "show": 1, "prefix": "EFD.NX-" },
			{ "snap": "NX 12.0",         			"production": 0, "show": 1, "prefix": "EFD.NX-" },
			{ "snap": "NX 1847-v1867",   			"production": 0, "show": 1, "prefix": "EFD.NX-" },
			{ "snap": "NX 1872-v1892",  			"production": 0, "show": 1, "prefix": "EFD.NX-" },
			{ "snap": "NX 1899-v1903",   			"production": 0, "show": 1, "prefix": "EFD.NX-" },
			{ "snap": "NX 1926-v1934",   			"production": 0, "show": 1, "prefix": "EFD.NX-" },
			{ "snap": "NX 1953-v1965",   			"production": 0, "show": 1, "prefix": "EFD.NX-" }
			],
		 "Simcenter 3d": [
			{ "snap": "Simcenter 2019.2-v1892", 	"production": 0, "show": 1, "prefix": "EFD.SC-" },
			{ "snap": "Simcenter 2020.1-v1919", 	"production": 0, "show": 1, "prefix": "EFD.SC-" },
			{ "snap": "Simcenter 2020.2-v1946", 	"production": 0, "show": 1, "prefix": "EFD.SC-" },
			{ "snap": "Simcenter 2021.1-v1961", 	"production": 0, "show": 1, "prefix": "EFD.SC-" }
			],
		 "Solid Edge": [
			{ "snap": "Solid Edge 2019", 			"production": 0, "show": 1, "prefix": "EFD.SE-" },
			{ "snap": "Solid Edge 2020", 			"production": 0, "show": 1, "prefix": "EFD.SE-" },
			{ "snap": "Solid Edge 2021", 			"production": 0, "show": 1, "prefix": "EFD.SE-" },
			{ "snap": "Solid Edge 2021-Student", 	"production": 0, "show": 1, "prefix": "EFD.SE-" }
			],
		 "SolidWorks": [
			{ "snap": "SW 2021 SP3.0",   			"production": 0, "show": 1, "prefix": "CFW-" }
			],
		 "without CAD": [
			{ "snap": "Office 2013",     			"production": 0, "show": 1, "prefix": "EFD.LAB-" }
			]

  }},
"Windows 10 x64-1": {
    "path": "e:\\Images\\Windows 10 x64-1\\Windows 10 x64-1.vmx",
    "lang": "English",
    "winver": "10",
	"win_name": "vm-win10-1",
    "cad_family": {
		 "Catia": [
			{ "snap": "Catia R19",       			"production": 0, "show": 0, "prefix": "EFD.V5-" },
			{ "snap": "Catia R20",       			"production": 0, "show": 0, "prefix": "EFD.V5-" },
			{ "snap": "Catia R21",       			"production": 0, "show": 1, "prefix": "EFD.V5-" },
			{ "snap": "Catia R22",       			"production": 0, "show": 0, "prefix": "EFD.V5-" },
			{ "snap": "Catia R23",       			"production": 0, "show": 0, "prefix": "EFD.V5-" },
			{ "snap": "Catia R24",       			"production": 0, "show": 1, "prefix": "EFD.V5-" },
			{ "snap": "Catia R25",       			"production": 0, "show": 1, "prefix": "EFD.V5-" },
			{ "snap": "Catia R26",       			"production": 0, "show": 1, "prefix": "EFD.V5-" },
			{ "snap": "Catia R27",       			"production": 0, "show": 1, "prefix": "EFD.V5-" },
			{ "snap": "Catia R28",       			"production": 0, "show": 1, "prefix": "EFD.V5-" },
			{ "snap": "Catia R29",       			"production": 0, "show": 1, "prefix": "EFD.V5-" },
			{ "snap": "Catia R30",       			"production": 0, "show": 1, "prefix": "EFD.V5-" }
			],
		 "Creo": [
	        { "snap": "Creo 2.0",        			"production": 0, "show": 0, "prefix": "EFD.PRO-" },
			{ "snap": "Creo 3.0",        			"production": 0, "show": 1, "prefix": "EFD.PRO-" },
			{ "snap": "Creo 4.0",        			"production": 0, "show": 1, "prefix": "EFD.PRO-" },
			{ "snap": "Creo 5.0",        			"production": 0, "show": 1, "prefix": "EFD.PRO-" },
			{ "snap": "Creo 6.0",        			"production": 0, "show": 1, "prefix": "EFD.PRO-" },
			{ "snap": "Creo 7.0",        			"production": 0, "show": 1, "prefix": "EFD.PRO-" }
			],
		 "NX": [
			{ "snap": "NX 10.0",         			"production": 0, "show": 1, "prefix": "EFD.NX-" },
			{ "snap": "NX 11.0",         			"production": 0, "show": 1, "prefix": "EFD.NX-" },
			{ "snap": "NX 12.0",         			"production": 0, "show": 1, "prefix": "EFD.NX-" },
			{ "snap": "NX 1847-v1867",   			"production": 0, "show": 1, "prefix": "EFD.NX-" },
			{ "snap": "NX 1872-v1892",  			"production": 0, "show": 1, "prefix": "EFD.NX-" },
			{ "snap": "NX 1899-v1915",   			"production": 0, "show": 1, "prefix": "EFD.NX-" },
			{ "snap": "NX 1926-v1934",   			"production": 0, "show": 1, "prefix": "EFD.NX-" },
			{ "snap": "NX 1953-v1965",   			"production": 0, "show": 1, "prefix": "EFD.NX-" }
			],
		 "Simcenter 3d": [
			{ "snap": "Simcenter 2019.2-v1892", 	"production": 0, "show": 1, "prefix": "EFD.SC-" },
			{ "snap": "Simcenter 2020.1-v1919", 	"production": 0, "show": 1, "prefix": "EFD.SC-" },
			{ "snap": "Simcenter 2020.2-v1946", 	"production": 0, "show": 1, "prefix": "EFD.SC-" },
			{ "snap": "Simcenter 2021.1-v1961", 	"production": 0, "show": 1, "prefix": "EFD.SC-" }
			],
		 "Solid Edge": [
			{ "snap": "Solid Edge 2019", 			"production": 0, "show": 1, "prefix": "EFD.SE-" },
			{ "snap": "Solid Edge 2020", 			"production": 0, "show": 1, "prefix": "EFD.SE-" },
			{ "snap": "Solid Edge 2021", 			"production": 0, "show": 1, "prefix": "EFD.SE-" },
			{ "snap": "Solid Edge 2022", 			"production": 0, "show": 1, "prefix": "EFD.SE-" }
			],
		 "SolidWorks": [
			{ "snap": "SW 2021 SP3.0",   			"production": 0, "show": 1, "prefix": "CFW-" }
			],
		 "without CAD": [
			{ "snap": "Office 2013",     			"production": 0, "show": 1, "prefix": "EFD.LAB-" }
			]

  }},
"Windows 10 x64-2": {
    "path": "e:\\Images\\Windows 10 x64-2\\Windows 10 x64-2.vmx",
    "lang": "English",
    "winver": "10",
	"win_name": "vm-win10-2",
    "cad_family": {
		 "Catia": [
			{ "snap": "Catia R19",       			"production": 0, "show": 1, "prefix": "EFD.V5-" },
			{ "snap": "Catia R20",       			"production": 0, "show": 1, "prefix": "EFD.V5-" },
			{ "snap": "Catia R21",       			"production": 1, "show": 1, "prefix": "EFD.V5-" },
			{ "snap": "Catia R22",       			"production": 0, "show": 1, "prefix": "EFD.V5-" },
			{ "snap": "Catia R23",       			"production": 0, "show": 1, "prefix": "EFD.V5-" },
			{ "snap": "Catia R24",       			"production": 0, "show": 1, "prefix": "EFD.V5-" },
			{ "snap": "Catia R25",       			"production": 1, "show": 1, "prefix": "EFD.V5-" },
			{ "snap": "Catia R26",       			"production": 1, "show": 1, "prefix": "EFD.V5-" },
			{ "snap": "Catia R27",       			"production": 1, "show": 1, "prefix": "EFD.V5-" },
			{ "snap": "Catia R28",       			"production": 1, "show": 1, "prefix": "EFD.V5-" },
			{ "snap": "Catia R29",       			"production": 1, "show": 1, "prefix": "EFD.V5-" },
			{ "snap": "Catia R30",       			"production": 0, "show": 1, "prefix": "EFD.V5-" }
			],
		 "Creo": [
	        { "snap": "Creo 2.0",        			"production": 0, "show": 1, "prefix": "EFD.PRO-" },
			{ "snap": "Creo 3.0",        			"production": 0, "show": 1, "prefix": "EFD.PRO-" },
			{ "snap": "Creo 4.0",        			"production": 0, "show": 1, "prefix": "EFD.PRO-" },
			{ "snap": "Creo 5.0",        			"production": 0, "show": 1, "prefix": "EFD.PRO-" },
			{ "snap": "Creo 6.0",        			"production": 0, "show": 1, "prefix": "EFD.PRO-" },
			{ "snap": "Creo 7.0",        			"production": 0, "show": 1, "prefix": "EFD.PRO-" }
			],
		 "NX": [
			{ "snap": "NX 9.0",          			"production": 0, "show": 1, "prefix": "EFD.NX-" },
			{ "snap": "NX 10.0",         			"production": 0, "show": 1, "prefix": "EFD.NX-" },
			{ "snap": "NX 11.0",         			"production": 1, "show": 1, "prefix": "EFD.NX-" },
			{ "snap": "NX 12.0",         			"production": 1, "show": 1, "prefix": "EFD.NX-" },
			{ "snap": "NX 1847-v1867",   			"production": 0, "show": 1, "prefix": "EFD.NX-" },
			{ "snap": "NX 1872-v1892",  			"production": 0, "show": 1, "prefix": "EFD.NX-" },
			{ "snap": "NX 1899-v1915",   			"production": 1, "show": 1, "prefix": "EFD.NX-" },
			{ "snap": "NX 1926-v1934",   			"production": 0, "show": 1, "prefix": "EFD.NX-" },
			{ "snap": "NX 1953-v1965",   			"production": 0, "show": 1, "prefix": "EFD.NX-" }
			],
		 "Simcenter 3d": [
			{ "snap": "Simcenter 2019.2-v1892", 	"production": 0, "show": 1, "prefix": "EFD.SC-" },
			{ "snap": "Simcenter 2020.1-v1919", 	"production": 0, "show": 1, "prefix": "EFD.SC-" },
			{ "snap": "Simcenter 2020.2-v1946", 	"production": 0, "show": 1, "prefix": "EFD.SC-" },
			{ "snap": "Simcenter 2021.1-v1961", 	"production": 0, "show": 1, "prefix": "EFD.SC-" }
			],
		 "Solid Edge": [
			{ "snap": "Solid Edge 2019", 			"production": 0, "show": 1, "prefix": "EFD.SE-" },
			{ "snap": "Solid Edge 2020", 			"production": 1, "show": 1, "prefix": "EFD.SE-" },
			{ "snap": "Solid Edge 2021", 			"production": 1, "show": 1, "prefix": "EFD.SE-" },
			{ "snap": "Solid Edge 2022", 			"production": 0, "show": 1, "prefix": "EFD.SE-" }
			],
		 "SolidWorks": [
			{ "snap": "SW 2021 SP3.0",   			"production": 1, "show": 1, "prefix": "CFW-" }
			],
		 "without CAD": [
			{ "snap": "Office 2013",     			"production": 1, "show": 1, "prefix": "EFD.LAB-" }
			]

  }},
"Windows 10 x64 German": {
    "path": "f:\\Images\\Windows 10 x64 German\\Windows 10 x64 German.vmx",
    "lang": "German",
    "winver": "10",
	"win_name": "vm-win10-ger",
    "cad_family": {
		 "Catia": [
			{ "snap": "Catia R25",       			"production": 0, "show": 1, "prefix": "EFD.V5-" },
			{ "snap": "Catia R26",       			"production": 1, "show": 1, "prefix": "EFD.V5-" },
			{ "snap": "Catia R27",       			"production": 0, "show": 1, "prefix": "EFD.V5-" },
			{ "snap": "Catia R28",       			"production": 0, "show": 1, "prefix": "EFD.V5-" },
			{ "snap": "Catia R30",       			"production": 0, "show": 1, "prefix": "EFD.V5-" }
			],
		 "Creo": [
	        { "snap": "Creo 2.0",        			"production": 0, "show": 1, "prefix": "EFD.PRO-" },
			{ "snap": "Creo 3.0",        			"production": 0, "show": 1, "prefix": "EFD.PRO-" },
			{ "snap": "Creo 5.0",        			"production": 0, "show": 1, "prefix": "EFD.PRO-" }
			],
		 "NX": [
			{ "snap": "NX 11.0",         			"production": 0, "show": 1, "prefix": "EFD.NX-" },
			{ "snap": "NX 12.0",         			"production": 0, "show": 1, "prefix": "EFD.NX-" },
			{ "snap": "NX 1899-v1915",   			"production": 0, "show": 1, "prefix": "EFD.NX-" }
			],
		 "Solid Edge": [
			{ "snap": "Solid Edge 2019", 			"production": 0, "show": 1, "prefix": "EFD.SE-" },
			{ "snap": "Solid Edge 2021", 			"production": 1, "show": 1, "prefix": "EFD.SE-" }
			],
		 "SolidWorks": [
			{ "snap": "SW 2021 SP3.0",   			"production": 1, "show": 1, "prefix": "CFW-" }
			],
		 "without CAD": [
			{ "snap": "Office 2013",     			"production": 1, "show": 1, "prefix": "EFD.LAB-" }
			]

  }},
"Windows 10 x64 Jap": {
    "path": "E:\\Images\\Windows 10 x64 Jap\\Windows 10 x64 Jap.vmx",
    "lang": "Japanese",
    "winver": "10",
	"win_name": "vm-win10-jap",
    "cad_family": {
		 "Catia": [
			 { "snap": "Catia R21",       			"production": 1, "show": 1, "prefix": "EFD.V5-" },
			 { "snap": "Catia R22",       			"production": 0, "show": 1, "prefix": "EFD.V5-" },
			 { "snap": "Catia R26",       			"production": 1, "show": 1, "prefix": "EFD.V5-" }
			],
		 "Creo": [
	        { "snap": "Creo 2.0",        			"production": 0, "show": 1, "prefix": "EFD.PRO-" },
			{ "snap": "Creo 3.0",        			"production": 0, "show": 1, "prefix": "EFD.PRO-" }
			],
		 "NX": [
			{ "snap": "NX 9.0",         			"production": 0, "show": 1, "prefix": "EFD.NX-" },
			{ "snap": "NX 11.0",         			"production": 1, "show": 1, "prefix": "EFD.NX-" },
			{ "snap": "NX 1899-v1915",   			"production": 0, "show": 1, "prefix": "EFD.NX-" }
			],
		 "Solid Edge": [
			{ "snap": "Solid Edge 2019", 			"production": 0, "show": 1, "prefix": "EFD.SE-" },
			{ "snap": "Solid Edge 2021", 			"production": 1, "show": 1, "prefix": "EFD.SE-" }
			],
		 "SolidWorks": [
			{ "snap": "SW 2021 SP3.0",   			"production": 1, "show": 1, "prefix": "CFW-" }
			],
		 "without CAD": [
			{ "snap": "Office 2013",     			"production": 1, "show": 1, "prefix": "EFD.LAB-" }
			]

  }},
"Windows 10 x64 Rus": {
    "path": "f:\\Images\\Windows 10 x64 Rus\\Windows 10 x64 Rus.vmx",
    "lang": "Russian",
    "winver": "10",
	"win_name": "vm-win10-rus",
    "cad_family": {
		 "Catia": [
			  { "snap": "Catia R21",       "production": 1, "show": 1, "prefix": "EFD.V5-" },
			  { "snap": "Catia R22",       "production": 0, "show": 1, "prefix": "EFD.V5-" },
			  { "snap": "Catia R24",       "production": 1, "show": 1, "prefix": "EFD.V5-" },
			  { "snap": "Catia R27",       "production": 1, "show": 1, "prefix": "EFD.V5-" },
			  { "snap": "Catia R28",       "production": 0, "show": 1, "prefix": "EFD.V5-" }
		 ],
		 "Creo": [
			  { "snap": "Creo 3.0",        "production": 0, "show": 1, "prefix": "EFD.PRO-" },
			  { "snap": "Creo 5.0",        "production": 0, "show": 1, "prefix": "EFD.PRO-" },
			  { "snap": "Creo 6.0",        "production": 0, "show": 1, "prefix": "EFD.PRO-" }
		 ],
		 "NX": [
			{ "snap": "NX 11.0",         			"production": 0, "show": 1, "prefix": "EFD.NX-" },
			{ "snap": "NX 12.0",         			"production": 1, "show": 1, "prefix": "EFD.NX-" },
			{ "snap": "NX 1899-v1915",   			"production": 0, "show": 1, "prefix": "EFD.NX-" },
			{ "snap": "NX 1953-v1965",   			"production": 1, "show": 1, "prefix": "EFD.NX-" }
			],
		 "Solid Edge": [
			{ "snap": "Solid Edge 2019", 			"production": 0, "show": 1, "prefix": "EFD.SE-" },
			{ "snap": "Solid Edge 2020", 			"production": 1, "show": 1, "prefix": "EFD.SE-" }
			],
		 "SolidWorks": [
			{ "snap": "SW 2021 SP3.0",   			"production": 1, "show": 1, "prefix": "CFW-" }
			],
		 "without CAD": [
			{ "snap": "Office 2013",     			"production": 1, "show": 1, "prefix": "EFD.LAB-" }
			]
  }},
"Windows 10 x64 Turkish": {
    "path": "f:\\Images\\Windows 10 x64 Turkish\\Windows 10 x64 Turkish.vmx",
    "lang": "Turkish",
    "winver": "10",
	"win_name": "vm-win10-tur",
    "cad_family": {
		 "Catia": [
			{ "snap": "Catia R25",       			"production": 0, "show": 1, "prefix": "EFD.V5-" },
			{ "snap": "Catia R27",       			"production": 1, "show": 1, "prefix": "EFD.V5-" },
			{ "snap": "Catia R28",       			"production": 0, "show": 1, "prefix": "EFD.V5-" }
			],
		 "Creo": [
			{ "snap": "Creo 3.0",        			"production": 0, "show": 1, "prefix": "EFD.PRO-" }
			],
		 "NX": [
			{ "snap": "NX 12.0",         			"production": 1, "show": 1, "prefix": "EFD.NX-" },
			{ "snap": "NX 1899-v1915",   			"production": 0, "show": 1, "prefix": "EFD.NX-" }
			],
		 "Solid Edge": [
			{ "snap": "Solid Edge 2019", 			"production": 0, "show": 1, "prefix": "EFD.SE-" }
			],
		 "SolidWorks": [
			{ "snap": "SW 2021 SP3.0",   			"production": 1, "show": 1, "prefix": "CFW-" }
			],
		 "without CAD": [
			{ "snap": "Office 2013",     			"production": 1, "show": 1, "prefix": "EFD.LAB-" }
			]

  }},
"Windows 7 x64 Chi": {
    "path": "d:\\Images\\Windows 7 x64 Chi\\Windows 7 x64 Chi.vmx",
    "lang": "Chinese",
    "winver": "7",
	"win_name": "vm-win7-chi",
    "cad_family": {
		 "Catia": [
		  { "snap": "Catia R19",       "production": 0, "show": 1, "prefix": "EFD.V5-" },
		  { "snap": "Catia R21",       "production": 1, "show": 1, "prefix": "EFD.V5-" },
		  { "snap": "Catia R22",       "production": 0, "show": 1, "prefix": "EFD.V5-" },
		  { "snap": "Catia R27",       "production": 1, "show": 1, "prefix": "EFD.V5-" },
		  { "snap": "Catia R28",       "production": 0, "show": 1, "prefix": "EFD.V5-" }
		 ],
		 "Creo": [
			{ "snap": "Creo 3.0",        			"production": 0, "show": 1, "prefix": "EFD.PRO-" },
			{ "snap": "Creo 4.0",        			"production": 0, "show": 1, "prefix": "EFD.PRO-" },
			{ "snap": "Creo 5.0",        			"production": 0, "show": 1, "prefix": "EFD.PRO-" }
			],
		 "NX": [
			{ "snap": "NX 9.0",          			"production": 0, "show": 1, "prefix": "EFD.NX-" },
			{ "snap": "NX 11.0",         			"production": 1, "show": 1, "prefix": "EFD.NX-" },
			{ "snap": "NX 1899-v1915",   			"production": 0, "show": 1, "prefix": "EFD.NX-" }
			],
		 "Solid Edge": [
			{ "snap": "Solid Edge 2019", 			"production": 0, "show": 1, "prefix": "EFD.SE-" }
			],
		 "without CAD": [
			{ "snap": "Office 2013",     			"production": 0, "show": 1, "prefix": "EFD.LAB-" }
			]
  }},
"Windows 7 x64 French": {
    "path": "d:\\Images\\Windows 7 x64 French\\Windows 7 x64 French.vmx",
    "lang": "French",
    "winver": "7",
	"win_name": "vm-win7-fre",
    "cad_family": {
		 "Catia": [
			  { "snap": "Catia R20",       "production": 0, "show": 1, "prefix": "EFD.V5-" },
			  { "snap": "Catia R22",       "production": 0, "show": 1, "prefix": "EFD.V5-" },
			  { "snap": "Catia R24",       "production": 1, "show": 1, "prefix": "EFD.V5-" },
			  { "snap": "Catia R25",       "production": 0, "show": 1, "prefix": "EFD.V5-" },
			  { "snap": "Catia R27",       "production": 1, "show": 1, "prefix": "EFD.V5-" },
			  { "snap": "Catia R28",       "production": 0, "show": 1, "prefix": "EFD.V5-" }
		 ],
		 "Creo": [
			{ "snap": "Creo 3.0",        			"production": 0, "show": 1, "prefix": "EFD.PRO-" }
			],
		 "NX": [
			{ "snap": "NX 9.0",          			"production": 0, "show": 1, "prefix": "EFD.NX-" },
			{ "snap": "NX 11.0",         			"production": 0, "show": 1, "prefix": "EFD.NX-" },
			{ "snap": "NX 1899-v1915",   			"production": 1, "show": 1, "prefix": "EFD.NX-" }
			],
		 "Solid Edge": [
			{ "snap": "Solid Edge 2019", 			"production": 0, "show": 1, "prefix": "EFD.SE-" }
			],
		 "without CAD": [
			{ "snap": "Office 2010",     			"production": 0, "show": 1, "prefix": "EFD.LAB-" }
			]
  }},
"Windows 7 x64 Italian": {
    "path": "d:\\Images\\Windows 7 x64 Italian\\Windows 7 x64 Italian.vmx",
    "lang": "Italian",
    "winver": "7",
	"win_name": "vm-win7-ita",
    "cad_family": {
		 "Catia": [
			  { "snap": "Catia R19",       "production": 0, "show": 0, "prefix": "EFD.V5-" },
			  { "snap": "Catia R23",       "production": 0, "show": 1, "prefix": "EFD.V5-" },
			  { "snap": "Catia R25",       "production": 1, "show": 1, "prefix": "EFD.V5-" },
			  { "snap": "Catia R27",       "production": 1, "show": 1, "prefix": "EFD.V5-" }
		 ],
		 "Creo": [
			{ "snap": "Creo 3.0",        			"production": 0, "show": 1, "prefix": "EFD.PRO-" }
			],
		 "NX": [
			{ "snap": "NX 9.0",          			"production": 0, "show": 1, "prefix": "EFD.NX-" },
			{ "snap": "NX 11.0",         			"production": 1, "show": 1, "prefix": "EFD.NX-" },
			{ "snap": "NX 1899-v1915",   			"production": 0, "show": 1, "prefix": "EFD.NX-" }
			],
		 "Solid Edge": [
			{ "snap": "Solid Edge 2020", 			"production": 0, "show": 1, "prefix": "EFD.SE-" }
			],
		 "without CAD": [
			{ "snap": "Office 2007",     			"production": 0, "show": 1, "prefix": "EFD.LAB-" }
			]
  }},
"Windows 7 x64 Jap new": {
    "path": "d:\\Images\\Windows 7 x64 Jap new\\Windows 7 x64 Jap new.vmx",
    "lang": "Japanese",
	"winver": "7",
	"win_name": "vm-win7-jap",
    "cad_family": {
		 "Catia": [
			  { "snap": "Catia R19",       "production": 0, "show": 0, "prefix": "EFD.V5-" },
			  { "snap": "Catia R22",       "production": 0, "show": 1, "prefix": "EFD.V5-" },
			  { "snap": "Catia R24",       "production": 0, "show": 1, "prefix": "EFD.V5-" },
			  { "snap": "Catia R25",       "production": 0, "show": 1, "prefix": "EFD.V5-" },
			  { "snap": "Catia R26",       "production": 0, "show": 1, "prefix": "EFD.V5-" },
			  { "snap": "Catia R28",       "production": 0, "show": 1, "prefix": "EFD.V5-" }
		 ],
		 "Creo": [
			 { "snap": "Creo 2.0",        "production": 0, "show": 1, "prefix": "EFD.PRO-" },
			 { "snap": "Creo 3.0",        "production": 0, "show": 1, "prefix": "EFD.PRO-" },
			 { "snap": "Creo 4.0",        "production": 0, "show": 1, "prefix": "EFD.PRO-" }
		 ],
		 "NX": [
			 { "snap": "NX 11.0",         "production": 0, "show": 1, "prefix": "EFD.NX-" },
			 { "snap": "NX 12.0",         "production": 0, "show": 1, "prefix": "EFD.NX-" },
			 { "snap": "NX 9.0",          "production": 0, "show": 0, "prefix": "EFD.NX-" }
		 ],
		 "Solid Edge": [
			 { "snap": "Solid Edge 2019", 			"production": 0, "show": 1, "prefix": "EFD.SE-" },
			 { "snap": "Solid Edge 2020", 			"production": 0, "show": 1, "prefix": "EFD.SE-" }
			],
		 "without CAD": [
			{ "snap": "Office 2010",     			"production": 0, "show": 1, "prefix": "EFD.LAB-" }
			]
  }},
"Windows 7 x64 Rus": {
    "path": "d:\\Images\\Windows 7 x64 Rus\\Windows 7 x64 Rus.vmx",
    "lang": "Russian",
	"winver": "7",
	"win_name": "vm-win10-rus",
    "cad_family": {
		 "Catia": [
			  { "snap": "Catia R21",       "production": 0, "show": 1, "prefix": "EFD.V5-" },
			  { "snap": "Catia R22",       "production": 0, "show": 1, "prefix": "EFD.V5-" },
			  { "snap": "Catia R24",       "production": 0, "show": 1, "prefix": "EFD.V5-" },
			  { "snap": "Catia R27",       "production": 0, "show": 1, "prefix": "EFD.V5-" },
			  { "snap": "Catia R28",       "production": 0, "show": 1, "prefix": "EFD.V5-" }
		 ],
		 "Creo": [
			  { "snap": "Creo 2.0",        "production": 0, "show": 1, "prefix": "EFD.PRO-" },
			  { "snap": "Creo 3.0",        "production": 0, "show": 1, "prefix": "EFD.PRO-" },
			  { "snap": "Creo 5.0",        "production": 0, "show": 1, "prefix": "EFD.PRO-" },
			  { "snap": "Creo 6.0",        "production": 0, "show": 1, "prefix": "EFD.PRO-" }
		 ],
		 "NX": [
			  { "snap": "NX 11.0",         "production": 0, "show": 1, "prefix": "EFD.NX-" },
			  { "snap": "NX 12.0",         "production": 0, "show": 1, "prefix": "EFD.NX-" },
			  { "snap": "NX 1899-v1915",   "production": 0, "show": 1, "prefix": "EFD.NX-" }
		 ],
		 "Solid Edge": [
			 { "snap": "Solid Edge 2019", 			"production": 0, "show": 1, "prefix": "EFD.SE-" }
			],
		 "without CAD": [
			{ "snap": "Office 2010",     			"production": 0, "show": 1, "prefix": "EFD.LAB-" }
			]
  }},
"Windows Server 2012 R2": {
    "path": "f:\\Images\\Windows Server 2012\\Windows Server 2012 R2.vmx",
    "lang": "English",
    "winver": "",
	"win_name": "vm-win2012",
	"cad_family": {
		"without CAD": [
			{ "snap": "Clear", "production": 0, "show": 1, "prefix": "-" }
		]
	}},
"Windows Server 2016": {
    "path": "C:\\Images\\Windows Server 2016\\Windows Server 2016.vmx",
    "lang": "English",
    "winver": "",
	"win_name": "vm-srv2016",
	"cad_family": {
		"without CAD": [
			{ "snap": "Clear", "production": 0, "show": 1, "prefix": "-" }
		]
	}},
"Windows Server 2016 AW": {
	"path": "D:\\Images\\Windows Server 2016 AW\\Windows Server 2016 AW.vmx",
    "lang": "English",
    "winver": "",
	"win_name": "plm-test",
	"cad_family": {
		"without CAD": [
			{ "snap": "21.01.2021", "production": 0, "show": 1, "prefix": "-" }
		]
	}},
"TC1123": {
    "path": "f:\\Images\\TC1123\\TC1123.vmx",
    "lang": "English",
    "winver": "",
	"win_name": "AEWIC1015A",
	"cad_family": {
		"without CAD": [
			{ "snap": "08.10.2019", "production": 0, "show": 1, "prefix": "-" }
		]
	}}
}
